wyrdle/__init__.py
wyrdle/backend/__init__.py
wyrdle/backend/hint.py
wyrdle/common/__init__.py
wyrdle/common/hint.py
wyrdle/common/words.py
wyrdle/frontend/__init__.py
wyrdle/frontend/game.py
wyrdle/frontend/guess.py
wyrdle/frontend/interface.py
wyrdle/frontend/player.py
wyrdle/frontend/tile.py
wyrdle-1.2.0.dist-info/entry_points.txt
wyrdle-1.2.0.dist-info/LICENSE
wyrdle-1.2.0.dist-info/WHEEL
wyrdle-1.2.0.dist-info/METADATA
wyrdle-1.2.0.dist-info/RECORD
