Metadata-Version: 2.1
Name: wyrdle
Version: 1.2.0
Summary: Wordle and bot in Python
Home-page: https://github.com/ColeFrench/wyrdle
License: MIT
Author: Cole French
Author-email: 16979554+ColeFrench@users.noreply.github.com
Requires-Python: >=3.9,<4.0
Classifier: Environment :: Console
Classifier: License :: OSI Approved :: MIT License
Classifier: Programming Language :: Python :: 3
Classifier: Programming Language :: Python :: 3.10
Classifier: Programming Language :: Python :: 3.9
Classifier: Topic :: Games/Entertainment :: Puzzle Games
Classifier: Topic :: Software Development :: Libraries :: Python Modules
Requires-Dist: colorama (>=0.4.4,<0.5.0)
Requires-Dist: sshkeyboard (>=2.3.1,<3.0.0)
Requires-Dist: typed-argument-parser (>=1.7.2,<2.0.0)
Project-URL: Repository, https://github.com/ColeFrench/wyrdle
